[
  {
    "id": 1,
    "title": "Додстер",
    "image": "https://media.dodostatic.net/image/r:584x584/01980cb92528769295aeb186fb501f8e.webp",
    "price": 249,
    "delivery": "Бесплатная доставка",
    "add_url": "/api/add_to_cart/1",
    "remove_url": "/api/remove_from_cart/1"
  },
  {
    "id": 2,
    "title": "Rich Tea",
    "image": "https://media.dodostatic.net/image/r:292x292/019a1089d33a7943a2c2c89e518c1341.webp",
    "price": 159,
    "delivery": "Бесплатная доставка",
    "add_url": "/api/add_to_cart/2",
    "remove_url": "/api/remove_from_cart/2"
  },
  {
    "id": 3,
    "title": "Креветки терияки",
    "image": "https://media.dodostatic.net/image/r:292x292/0198556badcf772484ba8ef325c9f09f.webp",
    "price": 379,
    "delivery": "Бесплатная доставка",
    "add_url": "/api/add_to_cart/3",
    "remove_url": "/api/remove_from_cart/3"
  },
  {
    "id": 4,
    "title": "Соус сырный",
    "image": "https://media.dodostatic.net/image/r:1875x1875/0197f86ac30a734eb384d710bb1789f3.webp",
    "price": 49,
    "delivery": "Бесплатная доставка",
    "add_url": "/api/add_to_cart/4",
    "remove_url": "/api/remove_from_cart/4"
  },
  {
    "id": 5,
    "title": "Пицца + напиток",
    "image": "https://media.dodostatic.net/image/r:1875x1875/0197c001ff39748ea72e0da6db8b13f0.webp",
    "price": 389,
    "delivery": "Бесплатная доставка",
    "add_url": "/api/add_to_cart/5",
    "remove_url": "/api/remove_from_cart/5"
  }
]